{"metadata":{"usedHelpers":[],"marked":[],"modules":{"imports":[],"exports":{"exported":[],"specifiers":[]}}},"options":{"filename":"/imports/ui/Main.js","filenameRelative":"/imports/ui/Main.js","env":{},"retainLines":false,"highlightCode":true,"suppressDeprecationMessages":false,"presets":[],"plugins":[[[],{"polyfill":false}],[[],null],[[],null],[[],null],[[],null],[[],null],[[],null],[[],null],[[],null],[[],null],[[],null],[[],null],[[],null],[[],null],[[],{"loose":true}],[[],{"loose":true}],[[],null],[[],{"loose":true}],[[],null],[[],null],[[],null],[[],null],[[],null],[[],null],[[],null],[[],{"loose":true}],[[],null],[[],null],[[],null],[[],null],[[],null],[[],null],[[],null],[[],null]],"ignore":[],"code":true,"metadata":true,"ast":false,"comments":true,"compact":false,"minified":false,"sourceMap":true,"sourceMaps":true,"sourceMapTarget":"/imports/ui/Main.js.map","sourceFileName":"/imports/ui/Main.js","babelrc":false,"sourceType":"module","moduleIds":false,"passPerPreset":false,"basename":"Main"},"ignored":false,"code":"// Include React and React-Router dependencies\nvar React = require('react');\nvar Router = require('react-router');\n\nvar bgColors = { \"Default\": \"#e3f2fd\",\n\t\"Blue\": \"#00B1E1\",\n\t\"Cyan\": \"#37BC9B\",\n\t\"Green\": \"#8CC152\",\n\t\"Red\": \"#E9573F\",\n\t\"Yellow\": \"#F6BB42\"\n};\n\nvar Main = React.createClass({\n\tdisplayName: 'Main',\n\n\n\trender: function render() {\n\n\t\treturn React.createElement(\n\t\t\t'div',\n\t\t\t{ className: 'main-container' },\n\t\t\tReact.createElement(\n\t\t\t\t'div',\n\t\t\t\t{ className: 'container' },\n\t\t\t\tReact.createElement(\n\t\t\t\t\t'nav',\n\t\t\t\t\t{ className: 'navbar navbar-dark bg-info' },\n\t\t\t\t\tReact.createElement(\n\t\t\t\t\t\t'div',\n\t\t\t\t\t\t{ className: 'container-fluid' },\n\t\t\t\t\t\tReact.createElement(\n\t\t\t\t\t\t\t'div',\n\t\t\t\t\t\t\t{ className: 'navbar-header' },\n\t\t\t\t\t\t\tReact.createElement(\n\t\t\t\t\t\t\t\t'button',\n\t\t\t\t\t\t\t\t{ type: 'button', className: 'navbar-toggle', 'data-toggle': 'collapse', 'data-target': '.navbar-ex1-collapse' },\n\t\t\t\t\t\t\t\tReact.createElement(\n\t\t\t\t\t\t\t\t\t'span',\n\t\t\t\t\t\t\t\t\t{ className: 'sr-only' },\n\t\t\t\t\t\t\t\t\t'Toggle navigation'\n\t\t\t\t\t\t\t\t),\n\t\t\t\t\t\t\t\tReact.createElement('span', { className: 'icon-bar' }),\n\t\t\t\t\t\t\t\tReact.createElement('span', { className: 'icon-bar' }),\n\t\t\t\t\t\t\t\tReact.createElement('span', { className: 'icon-bar' })\n\t\t\t\t\t\t\t)\n\t\t\t\t\t\t),\n\t\t\t\t\t\tReact.createElement(\n\t\t\t\t\t\t\t'div',\n\t\t\t\t\t\t\t{ className: 'collapse navbar-collapse navbar-ex1-collapse' },\n\t\t\t\t\t\t\tReact.createElement(\n\t\t\t\t\t\t\t\t'ul',\n\t\t\t\t\t\t\t\t{ className: 'nav navbar-nav navbar-left' },\n\t\t\t\t\t\t\t\tReact.createElement(\n\t\t\t\t\t\t\t\t\t'li',\n\t\t\t\t\t\t\t\t\tnull,\n\t\t\t\t\t\t\t\t\tReact.createElement('img', { src: 'https://s-media-cache-ak0.pinimg.com/originals/e2/5c/43/e25c43c6a65bdca84c72f0c58524fcd6.png', height: '50', width: '50' })\n\t\t\t\t\t\t\t\t),\n\t\t\t\t\t\t\t\tReact.createElement(\n\t\t\t\t\t\t\t\t\t'li',\n\t\t\t\t\t\t\t\t\tnull,\n\t\t\t\t\t\t\t\t\tReact.createElement(\n\t\t\t\t\t\t\t\t\t\t'a',\n\t\t\t\t\t\t\t\t\t\t{ href: '#/index' },\n\t\t\t\t\t\t\t\t\t\t'Home'\n\t\t\t\t\t\t\t\t\t)\n\t\t\t\t\t\t\t\t)\n\t\t\t\t\t\t\t),\n\t\t\t\t\t\t\tReact.createElement(\n\t\t\t\t\t\t\t\t'ul',\n\t\t\t\t\t\t\t\t{ className: 'nav navbar-nav navbar-right' },\n\t\t\t\t\t\t\t\tReact.createElement(\n\t\t\t\t\t\t\t\t\t'li',\n\t\t\t\t\t\t\t\t\tnull,\n\t\t\t\t\t\t\t\t\tReact.createElement('img', { src: 'http://blog.roblox.com/wp-content/uploads/2014/04/Points-Icon-700px.png', height: '50', width: '50' })\n\t\t\t\t\t\t\t\t),\n\t\t\t\t\t\t\t\tReact.createElement(\n\t\t\t\t\t\t\t\t\t'li',\n\t\t\t\t\t\t\t\t\tnull,\n\t\t\t\t\t\t\t\t\tReact.createElement(\n\t\t\t\t\t\t\t\t\t\t'a',\n\t\t\t\t\t\t\t\t\t\t{ href: '/Create' },\n\t\t\t\t\t\t\t\t\t\t'Create'\n\t\t\t\t\t\t\t\t\t)\n\t\t\t\t\t\t\t\t)\n\t\t\t\t\t\t\t),\n\t\t\t\t\t\t\tReact.createElement(\n\t\t\t\t\t\t\t\t'ul',\n\t\t\t\t\t\t\t\t{ className: 'nav navbar-nav navbar-right' },\n\t\t\t\t\t\t\t\tReact.createElement(\n\t\t\t\t\t\t\t\t\t'li',\n\t\t\t\t\t\t\t\t\tnull,\n\t\t\t\t\t\t\t\t\tReact.createElement('img', { src: 'http://www.engage2excel.com/wp-content/uploads/2015/09/Contests-icon.png', height: '50', width: '50' })\n\t\t\t\t\t\t\t\t),\n\t\t\t\t\t\t\t\tReact.createElement(\n\t\t\t\t\t\t\t\t\t'li',\n\t\t\t\t\t\t\t\t\tnull,\n\t\t\t\t\t\t\t\t\tReact.createElement(\n\t\t\t\t\t\t\t\t\t\t'a',\n\t\t\t\t\t\t\t\t\t\t{ href: '#/join' },\n\t\t\t\t\t\t\t\t\t\t'Join'\n\t\t\t\t\t\t\t\t\t)\n\t\t\t\t\t\t\t\t)\n\t\t\t\t\t\t\t),\n\t\t\t\t\t\t\tReact.createElement(\n\t\t\t\t\t\t\t\t'ul',\n\t\t\t\t\t\t\t\t{ className: 'nav navbar-nav navbar-right' },\n\t\t\t\t\t\t\t\tReact.createElement(\n\t\t\t\t\t\t\t\t\t'li',\n\t\t\t\t\t\t\t\t\tnull,\n\t\t\t\t\t\t\t\t\tReact.createElement('img', { src: 'http://www.freeiconspng.com/uploads/leaderboard-icon-3.png', height: '50', width: '50' })\n\t\t\t\t\t\t\t\t),\n\t\t\t\t\t\t\t\tReact.createElement(\n\t\t\t\t\t\t\t\t\t'li',\n\t\t\t\t\t\t\t\t\tnull,\n\t\t\t\t\t\t\t\t\tReact.createElement(\n\t\t\t\t\t\t\t\t\t\t'a',\n\t\t\t\t\t\t\t\t\t\t{ href: '/Leaderboards' },\n\t\t\t\t\t\t\t\t\t\t'Leaderboards'\n\t\t\t\t\t\t\t\t\t)\n\t\t\t\t\t\t\t\t)\n\t\t\t\t\t\t\t),\n\t\t\t\t\t\t\tReact.createElement(\n\t\t\t\t\t\t\t\t'ul',\n\t\t\t\t\t\t\t\t{ className: 'nav navbar-nav navbar-right navbar-for-responsiveness' },\n\t\t\t\t\t\t\t\tReact.createElement(\n\t\t\t\t\t\t\t\t\t'li',\n\t\t\t\t\t\t\t\t\tnull,\n\t\t\t\t\t\t\t\t\tReact.createElement('img', { src: 'https://openclipart.org/download/247319/abstract-user-flat-3.svg', height: '50', width: '50' })\n\t\t\t\t\t\t\t\t),\n\t\t\t\t\t\t\t\tReact.createElement(\n\t\t\t\t\t\t\t\t\t'li',\n\t\t\t\t\t\t\t\t\tnull,\n\t\t\t\t\t\t\t\t\tReact.createElement(\n\t\t\t\t\t\t\t\t\t\t'a',\n\t\t\t\t\t\t\t\t\t\t{ href: '#/profile' },\n\t\t\t\t\t\t\t\t\t\t'Profile'\n\t\t\t\t\t\t\t\t\t)\n\t\t\t\t\t\t\t\t)\n\t\t\t\t\t\t\t)\n\t\t\t\t\t\t)\n\t\t\t\t\t)\n\t\t\t\t),\n\t\t\t\tthis.props.children\n\t\t\t)\n\t\t);\n\t}\n});\n\n// Export the module back to the route\nmodule.export(\"default\",exports.default=(Main));","ast":null,"map":{"version":3,"sources":["/imports/ui/Main.js"],"names":[],"mappings":";AACA,IAAI,QAAQ,QAAQ,OAAR,CAAZ;AACA,IAAI,SAAS,QAAQ,cAAR,CAAb;;AAGA,IAAI,WAAW,EAAE,WAAW,SAAb;AACK,SAAQ,SADb;AAEK,SAAQ,SAFb;AAGK,UAAS,SAHd;AAIK,QAAO,SAJZ;AAKK,WAAU;AALf,CAAf;;AAQA,IAAI,OAAO,MAAM,WAAN,CAAkB;AAAA;;;AAE5B,SAAQ,kBAAU;;AAEjB,SAEC;AAAA;AAAA,KAAK,WAAU,gBAAf;AAGC;AAAA;AAAA,MAAK,WAAU,WAAf;AAEC;AAAA;AAAA,OAAK,WAAU,4BAAf;AACC;AAAA;AAAA,QAAK,WAAU,iBAAf;AACC;AAAA;AAAA,SAAK,WAAU,eAAf;AACC;AAAA;AAAA,UAAQ,MAAK,QAAb,EAAsB,WAAU,eAAhC,EAAgD,eAAY,UAA5D,EAAuE,eAAY,sBAAnF;AACC;AAAA;AAAA,WAAM,WAAU,SAAhB;AAAA;AAAA,SADD;AAEC,sCAAM,WAAU,UAAhB,GAFD;AAGC,sCAAM,WAAU,UAAhB,GAHD;AAIC,sCAAM,WAAU,UAAhB;AAJD;AADD,OADD;AAUC;AAAA;AAAA,SAAK,WAAU,8CAAf;AAEE;AAAA;AAAA,UAAI,WAAU,4BAAd;AACA;AAAA;AAAA;AAAI,sCAAK,KAAK,8FAAV,EAA0G,QAAO,IAAjH,EAAsH,OAAM,IAA5H;AAAJ,SADA;AAEA;AAAA;AAAA;AAAI;AAAA;AAAA,YAAG,MAAK,SAAR;AAAA;AAAA;AAAJ;AAFA,QAFF;AAeE;AAAA;AAAA,UAAI,WAAU,6BAAd;AACA;AAAA;AAAA;AAAI,sCAAK,KAAK,yEAAV,EAAqF,QAAO,IAA5F,EAAiG,OAAM,IAAvG;AAAJ,SADA;AAEA;AAAA;AAAA;AAAI;AAAA;AAAA,YAAG,MAAK,SAAR;AAAA;AAAA;AAAJ;AAFA,QAfF;AAoBN;AAAA;AAAA,UAAI,WAAU,6BAAd;AACQ;AAAA;AAAA;AAAI,sCAAK,KAAK,0EAAV,EAAsF,QAAO,IAA7F,EAAkG,OAAM,IAAxG;AAAJ,SADR;AAEQ;AAAA;AAAA;AAAI;AAAA;AAAA,YAAG,MAAK,QAAR;AAAA;AAAA;AAAJ;AAFR,QApBM;AAyBA;AAAA;AAAA,UAAI,WAAU,6BAAd;AACE;AAAA;AAAA;AAAI,sCAAK,KAAK,4DAAV,EAAwE,QAAO,IAA/E,EAAoF,OAAM,IAA1F;AAAJ,SADF;AAEE;AAAA;AAAA;AAAI;AAAA;AAAA,YAAG,MAAK,eAAR;AAAA;AAAA;AAAJ;AAFF,QAzBA;AA8BJ;AAAA;AAAA,UAAI,WAAU,uDAAd;AACM;AAAA;AAAA;AAAI,sCAAK,KAAK,kEAAV,EAA8E,QAAO,IAArF,EAA0F,OAAM,IAAhG;AAAJ,SADN;AAEM;AAAA;AAAA;AAAI;AAAA;AAAA,YAAG,MAAK,WAAR;AAAA;AAAA;AAAJ;AAFN;AA9BI;AAVD;AADD,KAFD;AAmDE,SAAK,KAAL,CAAW;AAnDb;AAHD,GAFD;AAiEA;AArE2B,CAAlB,CAAX;;;AAyEA,eAAe,IAAf","file":"/imports/ui/Main.js.map","sourcesContent":["// Include React and React-Router dependencies\nvar React = require('react');\nvar Router = require('react-router')\n\n\nvar bgColors = { \"Default\": \"#e3f2fd\",\n                    \"Blue\": \"#00B1E1\",\n                    \"Cyan\": \"#37BC9B\",\n                    \"Green\": \"#8CC152\",\n                    \"Red\": \"#E9573F\",\n                    \"Yellow\": \"#F6BB42\",\n};\n\nvar Main = React.createClass({\n\n\trender: function(){\n\n\t\treturn(\n\t\t\t/*We can only render a single div. So we need to group everything inside of this main-container one*/\n\t\t\t<div className=\"main-container\">\n\n\n\t\t\t\t<div className=\"container\">\n\t\t\t\t\t{/*Navbar*/}\n\t\t\t\t\t<nav className=\"navbar navbar-dark bg-info\">\n\t\t\t\t\t\t<div className=\"container-fluid\">\n\t\t\t\t\t\t\t<div className=\"navbar-header\">\n\t\t\t\t\t\t\t\t<button type=\"button\" className=\"navbar-toggle\" data-toggle=\"collapse\" data-target=\".navbar-ex1-collapse\">\n\t\t\t\t\t\t\t\t\t<span className=\"sr-only\">Toggle navigation</span>\n\t\t\t\t\t\t\t\t\t<span className=\"icon-bar\"></span>\n\t\t\t\t\t\t\t\t\t<span className=\"icon-bar\"></span>\n\t\t\t\t\t\t\t\t\t<span className=\"icon-bar\"></span>\n\t\t\t\t\t\t\t\t</button>\n\t\t\t\t\t\t\t</div>\n\t\t\t\t\t\n\t\t\t\t\t\t\t<div className=\"collapse navbar-collapse navbar-ex1-collapse\">\n\t\t\t\t\t\t\t\t\t\t\t\n\t\t\t\t\t\t\t\t\t<ul className=\"nav navbar-nav navbar-left\">\n\t\t\t\t\t\t\t\t\t<li><img src={'https://s-media-cache-ak0.pinimg.com/originals/e2/5c/43/e25c43c6a65bdca84c72f0c58524fcd6.png'} height='50' width='50'/></li>\n\t\t\t\t\t\t\t\t\t<li><a href=\"#/index\">Home</a></li>\n\t\t\t\t\t\t\t\t\t</ul>\n\t\t\t\t\t\n\n\n\n\t\t\t\t\t\t\n\t\t\t\t\t\t\t\t\t\n\n\t\t\t\t\t\t\t\n\n\t\t\t\t\t\t\t\t\t<ul className=\"nav navbar-nav navbar-right\">\n\t\t\t\t\t\t\t\t\t<li><img src={'http://blog.roblox.com/wp-content/uploads/2014/04/Points-Icon-700px.png'} height='50' width='50'/></li>\n\t\t\t\t\t\t\t\t\t<li><a href=\"/Create\">Create</a></li>\n\t\t\t\t\t\t\t\t\t</ul>\n\n\t<ul className=\"nav navbar-nav navbar-right\">\n\t\t\t\t\t\t\t\t\t<li><img src={'http://www.engage2excel.com/wp-content/uploads/2015/09/Contests-icon.png'} height='50' width='50'/></li>\n\t\t\t\t\t\t\t\t\t<li><a href=\"#/join\">Join</a></li>\n\t\t\t\t\t\t\t\t\t</ul>\n\n\t\t\t\t\t\t\t<ul className=\"nav navbar-nav navbar-right\">\n\t\t\t\t\t\t\t\t\t<li><img src={'http://www.freeiconspng.com/uploads/leaderboard-icon-3.png'} height='50' width='50'/></li>\n\t\t\t\t\t\t\t\t\t<li><a href=\"/Leaderboards\">Leaderboards</a></li>\n\t\t\t\t\t\t\t\t</ul>\n\n\t\t\t<ul className=\"nav navbar-nav navbar-right navbar-for-responsiveness\">\n\t\t\t\t\t\t\t\t\t<li><img src={'https://openclipart.org/download/247319/abstract-user-flat-3.svg'} height='50' width='50'/></li>\n\t\t\t\t\t\t\t\t\t<li><a href=\"#/profile\">Profile</a></li>\n\t\t\t\t\t\t\t\t\t</ul>\n\t\t\t\t\t\t\t</div>\n\t\t\t\t\t\t</div>\n\t\t\t\t\t</nav>\n\n\t\t\t\t\t{this.props.children}\n\n\t\t\n\t\t\t\t</div>\n\n\n\n\t\t\t</div>\n\t\t)\n\t}\n});\n\n// Export the module back to the route\nexport default Main;"]},"hash":"5e2e61638c80f434968ab459f8af770d9b402f4d"}
